__init__.py
bto.py
bto-1.0.0.dist-info/LICENSE
bto-1.0.0.dist-info/METADATA
bto-1.0.0.dist-info/WHEEL
bto-1.0.0.dist-info/entry_points.txt
bto-1.0.0.dist-info/top_level.txt
bto-1.0.0.dist-info/RECORD
