Metadata-Version: 2.1
Name: bto
Version: 1.0.0
Summary: [BTO]: multi-purpose cli tool (one-script-to-rule-them-all)
Author: Divinemonk
Maintainer: Divinemonk
License: MIT License
Project-URL: Homepage, https://github.com/Divinemonk/bto
Project-URL: Bug Tracker, https://github.com/Divinemonk/bto/issues
Project-URL: Changelog, https://github.com/me/spam/blob/m41n/CHANGELOG.md
Keywords: bto,tool,handy,divinemonk,all-in-one
Classifier: Development Status :: 5 - Production/Stable
Classifier: Programming Language :: Python :: 3
Classifier: License :: OSI Approved :: MIT License
Requires-Python: >=3.8
License-File: LICENSE
Requires-Dist: psutil
Requires-Dist: requests
Requires-Dist: pillow
Requires-Dist: rich
Requires-Dist: numpy
Requires-Dist: pytesseract
